README.md
setup.cfg
setup.py
baidu_acu_asr/__init__.py
baidu_acu_asr/asr_client.py
baidu_acu_asr/asr_client_factory.py
baidu_acu_asr/asr_product.py
baidu_acu_asr/audio_streaming_pb2.py
baidu_acu_asr/audio_streaming_pb2_grpc.py
baidu_acu_asr/generic_client_interceptor.py
baidu_acu_asr/header_manipulator_client_interceptor.py
baidu_acu_asr/request_header_validator_interceptor.py
baidu_acu_asr.egg-info/PKG-INFO
baidu_acu_asr.egg-info/SOURCES.txt
baidu_acu_asr.egg-info/dependency_links.txt
baidu_acu_asr.egg-info/requires.txt
baidu_acu_asr.egg-info/top_level.txt